README.md
setup.py
bayesian_trajectory_replay/__init__.py
bayesian_trajectory_replay/bayesian_trajectory_replay.py
bayesian_trajectory_replay/btr_helper_cauchy.pyx
bayesian_trajectory_replay/btr_helper_gaussian.pyx
bayesian_trajectory_replay/btr_helper_temporal.pyx
bayesian_trajectory_replay/data_log.py
bayesian_trajectory_replay/data_preprocessors.py
bayesian_trajectory_replay.egg-info/PKG-INFO
bayesian_trajectory_replay.egg-info/SOURCES.txt
bayesian_trajectory_replay.egg-info/dependency_links.txt
bayesian_trajectory_replay.egg-info/not-zip-safe
bayesian_trajectory_replay.egg-info/requires.txt
bayesian_trajectory_replay.egg-info/top_level.txt
test/test.py